airless/core/__init__.py
airless/core/base.py
airless/core/dto/__init__.py
airless/core/dto/base.py
airless/core/hook/__init__.py
airless/core/hook/base.py
airless/core/hook/datalake.py
airless/core/hook/email.py
airless/core/hook/file.py
airless/core/hook/llm.py
airless/core/hook/queue.py
airless/core/hook/secret.py
airless/core/operator/__init__.py
airless/core/operator/base.py
airless/core/operator/delay.py
airless/core/operator/error.py
airless/core/operator/redirect.py
airless/core/service/__init__.py
airless/core/service/base.py
airless/core/service/captcha.py
airless/core/utils/__init__.py
airless/core/utils/config.py
airless/core/utils/enum.py
airless_core-0.4.2.dist-info/METADATA
airless_core-0.4.2.dist-info/WHEEL
airless_core-0.4.2.dist-info/top_level.txt
airless_core-0.4.2.dist-info/RECORD
