Metadata-Version: 2.4
Name: airless-core
Version: 0.4.2
Summary: Airless is a package that aims to build a serverless and lightweight orchestration platform, creating workflows of multiple tasks being executed on FaaS platform
License: MIT License
Project-URL: Homepage, https://github.com/astercapital/airless
Project-URL: Bug Tracker, https://github.com/astercapital/airless/issues
Requires-Python: >=3.9
Requires-Dist: ndjson>=0.3.1
Requires-Dist: ndjson<0.4.0
Requires-Dist: python-dateutil>=2.0.0
Requires-Dist: python-dateutil<3.0.0
Requires-Dist: requests>=2.0.0
Requires-Dist: requests<3.0.0
Requires-Dist: deprecation>=2.1.0
